{"__ud_title":"NorthCombat初版","__ud_tags":["开服日记"],"__ud_update_time":1782383583590,"__ud_create_time":1782225641781,"__ud_draft":false,"type":"doc","content":[{"type":"heading","attrs":{"level":1,"id":null},"content":[{"type":"text","text":"NorthCombat初版"}]},{"type":"paragraph","content":[{"type":"text","text":"现在正在开发的进度"}]},{"type":"paragraph","content":[{"type":"text","text":"约百分之十吧"}]},{"type":"paragraph","content":[{"type":"text","text":"实现了基础功能"}]},{"type":"paragraph","content":[{"type":"text","text":"让玩家可以在服务器里开房间玩cs了"}]},{"type":"paragraph","content":[{"type":"text","text":"-未完待续"}]}]}